acp_factory/__init__.py
acp_factory/agent_handle.py
acp_factory/client_handler.py
acp_factory/factory.py
acp_factory/pushable.py
acp_factory/py.typed
acp_factory/session.py
acp_factory/types.py
acp_factory/providers/__init__.py
acp_factory/providers/claude_code.py
acp_factory/providers/codex.py
acp_factory/providers/gemini.py
acp_factory/providers/opencode.py
acp_factory-0.1.1.dist-info/METADATA
acp_factory-0.1.1.dist-info/WHEEL
acp_factory-0.1.1.dist-info/licenses/LICENSE
acp_factory-0.1.1.dist-info/RECORD
