Metadata-Version: 2.4
Name: acp-factory
Version: 0.1.1
Summary: A library for spawning and managing agents through the Agent Client Protocol (ACP)
Project-URL: Homepage, https://github.com/sudocode-ai/acp-factory
Project-URL: Documentation, https://github.com/sudocode-ai/acp-factory/tree/main/python#readme
Project-URL: Repository, https://github.com/sudocode-ai/acp-factory
Project-URL: Issues, https://github.com/sudocode-ai/acp-factory/issues
Project-URL: Changelog, https://github.com/sudocode-ai/acp-factory/blob/main/python/CHANGELOG.md
Author: Sudocode AI
License-Expression: MIT
License-File: LICENSE
Keywords: acp,agent,agent-client-protocol,ai,llm,sdk
Classifier: Development Status :: 3 - Alpha
Classifier: Intended Audience :: Developers
Classifier: License :: OSI Approved :: MIT License
Classifier: Programming Language :: Python :: 3
Classifier: Programming Language :: Python :: 3.10
Classifier: Programming Language :: Python :: 3.11
Classifier: Programming Language :: Python :: 3.12
Classifier: Programming Language :: Python :: 3.13
Classifier: Typing :: Typed
Requires-Python: >=3.10
Requires-Dist: agent-client-protocol>=0.7.0
Provides-Extra: dev
Requires-Dist: build>=1.0.0; extra == 'dev'
Requires-Dist: mypy>=1.10.0; extra == 'dev'
Requires-Dist: pytest-asyncio>=0.23.0; extra == 'dev'
Requires-Dist: pytest>=8.0.0; extra == 'dev'
Requires-Dist: ruff>=0.4.0; extra == 'dev'
Requires-Dist: twine>=5.0.0; extra == 'dev'
